<?xml version="1.0" encoding="UTF-8"?>
<points>
  <point>0.7949993,-0.6066408,0,0.6066408,0.7949993,0,0,0,1,483.9262,664.6465,25.1622</point>
  <point>0.7949993,-0.6066408,0,0.6066408,0.7949993,0,0,0,1,485.4106,663.4379,25.16642</point>
  <point>-0.4594713,0.8882151,0,-0.8882151,-0.4594713,0,0,0,1,457.5711,644.6005,32.7738</point>
  <point>-0.1171225,0.9931378,0,-0.9931378,-0.1171225,0,0,0,1,457.0965,645.9252,32.7738</point>
  <point>-0.1171225,0.9931378,0,-0.9931378,-0.1171225,0,0,0,1,456.8799,646.721,32.77379</point>
  <point>0.1520218,0.9883978,0,-0.9883978,0.1520218,0,0,0,1,457.0612,648.8458,32.7738</point>
  <point>0.1520218,0.9883978,0,-0.9883978,0.1520218,0,0,0,1,457.2369,649.7068,32.77379</point>
  <point>0.6613587,0.7500975,0,-0.7500975,0.6613587,0,0,0,1,458.0149,651.5107,32.77379</point>
  <point>0.6613587,0.7500975,0,-0.7500975,0.6613587,0,0,0,1,458.6208,652.27,32.77379</point>
  <point>0.9529053,0.3033371,0,-0.3033371,0.9529053,0,0,0,1,460.2005,653.2994,32.7738</point>
  <point>0.9529053,0.3033371,0,-0.3033371,0.9529053,0,0,0,1,461.0737,653.6522,32.76782</point>
  <point>0.9899822,-0.1413419,0,0.1413419,0.9899822,0,0,0,1,463.0656,653.8859,32.7738</point>
  <point>0.9899822,-0.1413419,0,0.1413419,0.9899822,0,0,0,1,463.8947,653.81,32.7738</point>
  <point>0.8128408,-0.5825229,0,0.5825229,0.8128408,0,0,0,1,465.8756,652.9737,32.77379</point>
  <point>0.8128408,-0.5825229,0,0.5825229,0.8128408,0,0,0,1,466.5807,652.4609,32.7738</point>
  <point>0.4519888,-0.8920481,0,0.8920481,0.4519888,0,0,0,1,467.9783,650.9133,32.77379</point>
  <point>0.04896409,-0.9988226,0,0.9988226,0.04896409,0,0,0,1,468.7967,648.0916,32.7738</point>
  <point>0.8128417,-0.5825236,0,0.5825236,0.8128417,0,0,0,1,441.2561,629.9196,32.30176</point>
  <point>0.8128417,-0.5825236,0,0.5825236,0.8128417,0,0,0,1,442.9975,628.6355,32.30869</point>
  <point>0.8128417,-0.5825236,0,0.5825236,0.8128417,0,0,0,1,443.8014,628.0388,32.3111</point>
  <point>0.8128417,-0.5825236,0,0.5825236,0.8128417,0,0,0,1,445.3228,626.8558,32.31548</point>
  <point>0.7571955,-0.653223,0,0.653223,0.7571955,0,0,0,1,442.3634,629.5378,27.70367</point>
  <point>0.5912654,0.8065059,0,-0.8065059,0.5912654,0,0,0,1,510.9656,680.7163,16.94993</point>
  <point>0.683562,0.7299244,0,-0.7299244,0.683562,0,0,0,1,509.2085,684.7394,16.888</point>
  <point>0.683562,0.7299244,0,-0.7299244,0.683562,0,0,0,1,511.0539,685.7493,16.84048</point>
  <point>0.7849649,0.6195779,0,-0.6195779,0.7849649,0,0,0,1,512.7166,686.7783,16.8111</point>
  <point>0.7849649,0.6195779,0,-0.6195779,0.7849649,0,0,0,1,514.355,688.1439,16.56317</point>
  <point>0.7849649,0.6195779,0,-0.6195779,0.7849649,0,0,0,1,512.254,683.0799,16.63974</point>
  <point>0.7849649,0.6195779,0,-0.6195779,0.7849649,0,0,0,1,514.1912,684.0439,16.67013</point>
  <point>0.7849649,0.6195779,0,-0.6195779,0.7849649,0,0,0,1,515.5385,685.7448,16.51661</point>
  <point>-0.9416363,0.3367047,0,-0.3367047,-0.9416363,0,0,0,1,528.0221,699.7966,19.41666</point>
  <point>-0.9416363,0.3367047,0,-0.3367047,-0.9416363,0,0,0,1,526.1722,700.2053,19.46291</point>
  <point>-0.9416363,0.3367047,0,-0.3367047,-0.9416363,0,0,0,1,524.0392,700.9438,19.62253</point>
  <point>-0.8000765,0.5999388,0,-0.5999388,-0.8000765,0,0,0,1,522.2433,702.1546,19.80096</point>
  <point>-0.8000765,0.5999388,0,-0.5999388,-0.8000765,0,0,0,1,520.6475,703.3603,19.79574</point>
  <point>-0.587049,0.8095827,0,-0.8095827,-0.587049,0,0,0,1,502.547,718.2227,17.67925</point>
  <point>-0.587049,0.8095827,0,-0.8095827,-0.587049,0,0,0,1,503.5392,716.1678,17.79477</point>
  <point>-0.6797442,0.7334837,0,-0.7334837,-0.6797442,0,0,0,1,504.8598,714.0965,17.79477</point>
  <point>-0.7014396,0.7127644,0,-0.7127644,-0.7014396,0,0,0,1,507.4049,712.3702,17.5397</point>
  <point>-0.6110688,0.7916096,0,-0.7916096,-0.6110688,0,0,0,1,515.8481,706.8395,19.71613</point>
  <point>-0.6110688,0.7916096,0,-0.7916096,-0.6110688,0,0,0,1,515.9416,709.3181,19.60435</point>
  <point>0.9952099,0.09803189,0,-0.09803189,0.9952099,0,0,0,1,509.6414,728.038,36.96879</point>
  <point>0.9097442,0.4152332,0,-0.4152332,0.9097442,0,0,0,1,507.7361,727.4601,36.96473</point>
  <point>0.8687417,0.4953192,0,-0.4953192,0.8687417,0,0,0,1,506.7288,726.7338,36.96879</point>
  <point>0.4641045,0.8858108,0,-0.8858108,0.4641045,0,0,0,1,505.4244,725.4094,36.92456</point>
  <point>0.4373254,0.8993333,0,-0.8993333,0.4373254,0,0,0,1,504.9304,724.4899,36.94769</point>
  <point>0.06257014,0.9980679,0,-0.9980679,0.06257014,0,0,0,1,504.4383,722.6029,36.96879</point>
  <point>0.06257014,0.9980679,0,-0.9980679,0.06257014,0,0,0,1,504.3561,721.6272,36.96879</point>
  <point>-0.2930346,0.9561309,0,-0.9561309,-0.2930346,0,0,0,1,504.8691,719.4877,36.96879</point>
  <point>-0.4326266,0.9016041,0,-0.9016041,-0.4326266,0,0,0,1,505.2414,718.6188,36.96879</point>
  <point>-0.7429199,0.6694223,0,-0.6694223,-0.7429199,0,0,0,1,506.6264,717.0309,36.96257</point>
  <point>-0.7429199,0.6694223,0,-0.6694223,-0.7429199,0,0,0,1,507.24,716.4668,36.96469</point>
  <point>0.1223055,0.9925215,0,-0.9925215,0.1223055,0,0,0,1,565.1885,685.0255,26.74487</point>
  <point>0.1223055,0.9925215,0,-0.9925215,0.1223055,0,0,0,1,563.3619,686.8085,26.20169</point>
  <point>0.1223055,0.9925215,0,-0.9925215,0.1223055,0,0,0,1,561.7214,688.123,25.84863</point>
  <point>-0.1764673,0.984336,0,-0.984336,-0.1764673,0,0,0,1,573.0715,706.4473,45.94791</point>
  <point>-0.1764673,0.984336,0,-0.984336,-0.1764673,0,0,0,1,573.5463,704.0714,45.94237</point>
  <point>-0.1764673,0.984336,0,-0.984336,-0.1764673,0,0,0,1,573.7255,703.0057,45.93725</point>
  <point>-0.2642238,0.9644915,0,-0.9644915,-0.2642238,0,0,0,1,574.3372,700.9497,45.93946</point>
  <point>-0.2642238,0.9644915,0,-0.9644915,-0.2642238,0,0,0,1,574.5671,699.951,45.9384</point>
  <point>-0.2642238,0.9644915,0,-0.9644915,-0.2642238,0,0,0,1,575.3675,697.7446,45.93767</point>
  <point>-0.2642238,0.9644915,0,-0.9644915,-0.2642238,0,0,0,1,575.65,696.9259,45.93681</point>
  <point>-0.4053887,0.9141763,0,-0.9141763,-0.4053887,0,0,0,1,576.7426,694.9724,45.93786</point>
  <point>-0.8885675,0.4587581,0,-0.4587581,-0.8885675,0,0,0,1,589.8353,687.3234,51.30624</point>
  <point>-0.6474295,0.7621323,0,-0.7621323,-0.6474295,0,0,0,1,587.256,688.8958,51.30624</point>
  <point>0.9026152,0.4304588,0,-0.4304588,0.9026152,0,0,0,1,466.8845,739.8386,20.28775</point>
  <point>0.9026152,0.4304588,0,-0.4304588,0.9026152,0,0,0,1,464.4905,740.34,20.2705</point>
  <point>-0.9979938,-0.06336398,0,0.06336398,-0.9979938,0,0,0,1,462.2483,753.4087,30.5588</point>
  <point>-0.874405,0.4852031,0,-0.4852031,-0.874405,0,0,0,1,508.2387,716.0969,36.96879</point>
  <point>0.9538485,-0.300294,0,0.300294,0.9538485,0,0,0,1,558.1921,640.2958,60.32924</point>
  <point>0.9993892,-0.03499331,0,0.03499331,0.9993892,0,0,0,1,555.3947,640.9316,60.32924</point>
  <point>0.9026123,0.4304582,0,-0.4304582,0.9026123,0,0,0,1,552.4167,640.7267,60.32924</point>
  <point>0.7744206,0.6326737,0,-0.6326737,0.7744206,0,0,0,1,550.1572,639.435,60.32924</point>
  <point>0.527621,0.8494816,0,-0.8494816,0.527621,0,0,0,1,548.0801,637.6868,60.32924</point>
  <point>-0.5763081,0.8172336,0,-0.8172336,-0.5763081,0,0,0,1,598.1439,683.921,49.15874</point>
  <point>-0.5763081,0.8172336,0,-0.8172336,-0.5763081,0,0,0,1,600.2323,681.2269,49.15121</point>
  <point>-0.5763081,0.8172336,0,-0.8172336,-0.5763081,0,0,0,1,602.1317,678.5054,49.14424</point>
  <point>-0.5515354,0.8341525,0,-0.8341525,-0.5515354,0,0,0,1,603.9605,675.686,49.13744</point>
  <point>-0.5515354,0.8341524,0,-0.8341524,-0.5515354,0,0,0,1,605.7667,672.918,49.13443</point>
  <point>-0.6242756,0.7812051,0,-0.7812051,-0.6242756,0,0,0,1,607.5652,670.029,49.13222</point>
  <point>-0.4053887,0.9141763,0,-0.9141763,-0.4053887,0,0,0,1,577.1219,694.2422,45.93738</point>
  <point>-0.4859128,0.8740407,0,-0.8740407,-0.4859128,0,0,0,1,578.3137,692.3406,45.93718</point>
  <point>-0.4859128,0.8740407,0,-0.8740407,-0.4859128,0,0,0,1,578.8845,691.4808,45.93678</point>
  <point>-0.4859128,0.8740407,0,-0.8740407,-0.4859128,0,0,0,1,580.9041,689.1331,46.12637</point>
  <point>-0.9959638,0.0901002,0,-0.0901002,-0.9959638,0,0,0,1,495.02,698.0367,20.32159</point>
  <point>-0.1008475,-0.9949334,0,0.9949334,-0.1008475,0,0,0,1,493.248,697.2173,20.32044</point>
  <point>-0.1008475,-0.9949334,0,0.9949334,-0.1008475,0,0,0,1,493.2332,695.6206,20.32207</point>
  <point>-0.1008475,-0.9949334,0,0.9949334,-0.1008475,0,0,0,1,493.0255,693.8538,20.32478</point>
  <point>0.5528644,0.8332737,0,-0.8332737,0.5528644,0,0,0,1,487.3162,670.094,20.39712</point>
  <point>-0.7340091,0.6791442,0,-0.6791442,-0.7340091,0,0,0,1,472.9614,725.5157,19.07247</point>
  <point>0.714422,0.699717,0,-0.699717,0.714422,0,0,0,1,451.6236,642.2532,22.05924</point>
  <point>0.1065935,0.9943027,0,-0.9943027,0.1065935,0,0,0,1,489.238,703.837,20.31927</point>
  <point>0.9268,0.3755598,0,-0.3755598,0.9268,0,0,0,1,471.473,653.5077,21.58635</point>
  <point>-0.2514754,0.9678699,0,-0.9678699,-0.2514754,0,0,0,1,460.4355,739.5029,20.28098</point>
  <point>-0.2514754,0.9678699,0,-0.9678699,-0.2514754,0,0,0,1,457.6369,750.4827,17.94762</point>
  <point>-0.6919659,0.7219388,0,-0.7219388,-0.6919659,0,0,0,1,468.9574,785.9889,17.64673</point>
  <point>-0.5262675,0.8503228,0,-0.8503228,-0.5262675,0,0,0,1,467.4046,732.0345,19.07685</point>
  <point>0.9118615,0.4104979,0,-0.4104979,0.9118615,0,0,0,1,460.087,653.708,22.27683</point>
  <point>-0.2514754,0.9678699,0,-0.9678699,-0.2514754,0,0,0,1,459.6339,742.2062,17.92874</point>
  <point>0.3947515,0.9187903,0,-0.9187903,0.3947515,0,0,0,1,488.1663,671.9996,20.39746</point>
  <point>0.602633,0.7980186,0,-0.7980186,0.602633,0,0,0,1,437.75,626.345,27.70859</point>
  <point>0.1065935,0.9943027,0,-0.9943027,0.1065935,0,0,0,1,489.904,696.521,21.54025</point>
  <point>0.9997749,-0.02181318,0,0.02181318,0.9997749,0,0,0,1,488.7687,692.2582,25.75119</point>
  <point>-0.5262675,0.8503228,0,-0.8503228,-0.5262675,0,0,0,1,466.8391,732.8779,19.07505</point>
  <point>0.6659721,0.7459766,0,-0.7459766,0.6659721,0,0,0,1,477.885,663.256,20.56626</point>
  <point>-0.9911256,0.133014,0,-0.133014,-0.9911256,0,0,0,1,495.7108,683.832,25.75111</point>
  <point>0.714422,0.699717,0,-0.699717,0.714422,0,0,0,1,452.1831,642.8544,22.05837</point>
  <point>0.3947515,0.9187903,0,-0.9187903,0.3947515,0,0,0,1,488.4716,672.874,20.39726</point>
  <point>0.7930494,0.6091604,0,-0.6091604,0.7930494,0,0,0,1,474.1185,655.3323,21.14994</point>
  <point>0.6018354,0.7986219,0,-0.7986219,0.6018354,0,0,0,1,446.2062,635.6895,22.05853</point>
  <point>-0.9946696,0.1032249,0,-0.1032249,-0.9946696,0,0,0,1,490.4301,684.2513,25.75111</point>
  <point>0.714422,0.699717,0,-0.699717,0.714422,0,0,0,1,448.0069,638.0599,22.05909</point>
  <point>-0.2514754,0.9678699,0,-0.9678699,-0.2514754,0,0,0,1,457.4264,751.4729,17.94802</point>
  <point>-0.2514754,0.9678699,0,-0.9678699,-0.2514754,0,0,0,1,458.847,745.3563,17.9466</point>
  <point>-0.5347489,-0.845022,0,0.845022,-0.5347489,0,0,0,1,484.6744,715.5895,24.99502</point>
  <point>-0.5347489,-0.845022,0,0.845022,-0.5347489,0,0,0,1,487.2768,719.9427,24.9973</point>
  <point>0.5377755,0.8430882,0,-0.8430882,0.5377755,0,0,0,1,456.724,651.258,26.89197</point>
  <point>-0.5119007,0.8590586,0,-0.8590586,-0.5119007,0,0,0,1,488.3535,686.0935,25.75111</point>
  <point>0.9268,0.3755598,0,-0.3755598,0.9268,0,0,0,1,472.2441,653.9314,21.47083</point>
  <point>0.2238833,0.9746186,0,-0.9746186,0.2238833,0,0,0,1,490.1053,678.9225,20.39617</point>
  <point>-0.8283768,0.5601714,0,-0.5601714,-0.8283768,0,0,0,1,482.81,715.976,20.40317</point>
  <point>-0.8507485,0.5255954,0,-0.5255954,-0.8507485,0,0,0,1,489.8527,684.532,25.75093</point>
  <point>-0.7920787,0.6104238,0,-0.6104238,-0.7920787,0,0,0,1,476.1243,722.8461,19.07074</point>
  <point>0.9790626,0.2035676,0,-0.2035676,0.9790626,0,0,0,1,469.4649,652.5734,21.8975</point>
  <point>-0.6919639,0.721936,0,-0.721936,-0.6919639,0,0,0,1,487.6232,715.7345,20.27511</point>
  <point>-0.7920787,0.6104238,0,-0.6104238,-0.7920787,0,0,0,1,475.3494,723.4149,19.07087</point>
  <point>-0.6005633,0.7995812,0,-0.7995812,-0.6005633,0,0,0,1,468.6414,730.1869,19.07066</point>
  <point>-0.7920787,0.6104238,0,-0.6104238,-0.7920787,0,0,0,1,473.6435,724.8398,19.0719</point>
  <point>-0.6474287,0.7621301,0,-0.7621301,-0.6474287,0,0,0,1,471.3794,726.9274,19.07153</point>
  <point>-0.6474287,0.7621301,0,-0.7621301,-0.6474287,0,0,0,1,470.7563,727.6892,19.07249</point>
  <point>-0.3655321,0.9308015,0,-0.9308015,-0.3655321,0,0,0,1,489.5528,713.1724,20.26883</point>
  <point>-0.6005633,0.7995812,0,-0.7995812,-0.6005633,0,0,0,1,469.2368,729.3944,19.07178</point>
  <point>-0.8594577,0.5112125,0,-0.5112125,-0.8594577,0,0,0,1,483.8435,715.4795,24.98712</point>
  <point>-0.8594577,0.5112125,0,-0.5112125,-0.8594577,0,0,0,1,477.947,721.7015,19.07088</point>
  <point>0.6018358,0.7986223,0,-0.7986223,0.6018358,0,0,0,1,485.2898,666.5208,20.39127</point>
  <point>0.9026154,0.4304593,0,-0.4304593,0.9026154,0,0,0,1,460.3692,740.4615,20.27798</point>
  <point>0.5528644,0.8332737,0,-0.8332737,0.5528644,0,0,0,1,486.86,669.2573,20.39676</point>
  <point>0.3105745,0.9505516,0,-0.9505516,0.3105745,0,0,0,1,489.452,675.832,20.39767</point>
  <point>0.6018358,0.7986223,0,-0.7986223,0.6018358,0,0,0,1,485.7371,667.2606,20.39641</point>
  <point>-0.2223304,0.9749742,0,-0.9749742,-0.2223304,0,0,0,1,490.8016,710.3407,20.26642</point>
  <point>-0.2223304,0.9749742,0,-0.9749742,-0.2223304,0,0,0,1,490.5212,711.1643,20.26637</point>
  <point>-0.2514754,0.9678699,0,-0.9678699,-0.2514754,0,0,0,1,462.2884,734.5,20.28615</point>
  <point>0.6711791,0.741298,0,-0.741298,0.6711791,0,0,0,1,476.8648,658.0963,20.62351</point>
  <point>0.6711791,0.741298,0,-0.741298,0.6711791,0,0,0,1,477.0848,662.2565,25.14839</point>
  <point>0.7949993,-0.6066408,0,0.6066408,0.7949993,0,0,0,1,483.2462,665.2855,25.15983</point>
  <point>-0.7817147,0.6236634,0,-0.6236634,-0.7817147,0,0,0,1,481.015,658.1873,25.16087</point>
  <point>-0.7817147,0.6236634,0,-0.6236634,-0.7817147,0,0,0,1,478.8405,660.0253,25.16182</point>
  <point>-0.7817147,0.6236634,0,-0.6236634,-0.7817147,0,0,0,1,477.1309,661.4442,25.15734</point>
  <point>0.9615706,0.274616,0,-0.274616,0.9615706,0,0,0,1,491.2437,706.7591,25.75112</point>
  <point>0.5163815,0.8563768,0,-0.8563768,0.5163815,0,0,0,1,489.5365,705.4572,25.75112</point>
  <point>0.4101492,0.9120354,0,-0.9120354,0.4101492,0,0,0,1,489.1553,704.7628,25.75112</point>
  <point>0.1223055,0.9925078,0,-0.9925078,0.1223055,0,0,0,1,488.7976,702.7701,25.75112</point>
  <point>0.1223055,0.9925078,0,-0.9925078,0.1223055,0,0,0,1,488.7151,701.945,25.75112</point>
  <point>-0.9973211,0.07334235,0,-0.07334235,-0.9973211,0,0,0,1,488.6711,699.1753,25.75112</point>
  <point>0.1223058,0.9925062,0,-0.9925062,0.1223058,0,0,0,1,488.5368,699.8938,25.75112</point>
  <point>0.1520214,0.988391,0,-0.988391,0.1520214,0,0,0,1,489.8509,697.8816,25.75106</point>
  <point>0.1520214,0.988391,0,-0.988391,0.1520214,0,0,0,1,489.6885,696.1611,25.75107</point>
  <point>0.1520214,0.9883909,0,-0.9883909,0.1520214,0,0,0,1,489.6441,695.3094,25.75107</point>
  <point>-0.9543276,-0.298774,0,0.298774,-0.9543276,0,0,0,1,462.5618,733.9172,20.27876</point>
  <point>0.3670144,0.9302177,0,-0.9302177,0.3670144,0,0,0,1,489.2141,674.9579,20.39781</point>
  <point>-0.5347489,-0.845022,0,0.845022,-0.5347489,0,0,0,1,485.6454,717.4175,24.99936</point>
  <point>-0.4477118,0.8941808,0,-0.8941808,-0.4477118,0,0,0,1,489.1334,713.9409,20.27294</point>
  <point>-0.9892811,0.1460701,0,-0.1460701,-0.9892811,0,0,0,1,461.1481,753.5739,30.5588</point>
  <point>0.714422,0.699717,0,-0.699717,0.714422,0,0,0,1,454.4876,645.16,22.062</point>
  <point>0.6659721,0.7459766,0,-0.7459766,0.6659721,0,0,0,1,479.896,665.84,20.56497</point>
  <point>-0.2514754,0.9678699,0,-0.9678699,-0.2514754,0,0,0,1,459.1119,744.4175,17.94185</point>
  <point>0.1065935,0.9943027,0,-0.9943027,0.1065935,0,0,0,1,489.803,694.391,21.54025</point>
  <point>0.1520214,0.9883909,0,-0.9883909,0.1520214,0,0,0,1,489.4942,693.2573,25.75115</point>
  <point>-0.014203,0.9999017,0,-0.9999017,-0.014203,0,0,0,1,491.2869,708.2451,20.26776</point>
  <point>-0.9563438,0.2922661,0,-0.2922661,-0.9563438,0,0,0,1,459.7277,753.2982,20.03962</point>
  <point>0.06257108,0.9980529,0,-0.9980529,0.06257108,0,0,0,1,487.9018,688.7218,25.75111</point>
  <point>0.714422,0.699717,0,-0.699717,0.714422,0,0,0,1,453.8237,644.5167,22.06395</point>
  <point>0.1065935,0.9943027,0,-0.9943027,0.1065935,0,0,0,1,488.416,690.499,20.32731</point>
  <point>0.7930494,0.6091604,0,-0.6091604,0.7930494,0,0,0,1,474.7157,655.8721,21.03894</point>
  <point>0.1065935,0.9943027,0,-0.9943027,0.1065935,0,0,0,1,488.192,687.594,20.31931</point>
  <point>0.6018354,0.7986219,0,-0.7986219,0.6018354,0,0,0,1,445.5887,634.8629,22.05822</point>
  <point>0.8225027,-0.5687624,0,0.5687624,0.8225027,0,0,0,1,439.6119,633.5941,23.79306</point>
  <point>0.6486402,0.7610953,0,-0.7610953,0.6486402,0,0,0,1,439.1898,633.0914,23.79436</point>
  <point>-0.9646804,0.2634487,0,-0.2634487,-0.9646804,0,0,0,1,460.2761,753.6625,30.5588</point>
  <point>0.6486402,0.7610953,0,-0.7610953,0.6486402,0,0,0,1,435.8,628.6524,23.80085</point>
  <point>-0.5262693,0.8503266,0,-0.8503266,-0.5262693,0,0,0,1,456.3857,756.4515,30.5588</point>
  <point>0.06257108,0.9980529,0,-0.9980529,0.06257108,0,0,0,1,487.9708,689.5118,25.75111</point>
  <point>-0.4206902,0.9072125,0,-0.9072125,-0.4206902,0,0,0,1,455.968,757.1227,30.5588</point>
  <point>0.5276251,0.8494867,0,-0.8494867,0.5276251,0,0,0,1,481.4509,723.4541,25.00377</point>
  <point>0.04578179,0.9989591,0,-0.9989591,0.04578179,0,0,0,1,455.4711,758.8251,30.5588</point>
  <point>0.5276251,0.8494867,0,-0.8494867,0.5276251,0,0,0,1,479.8915,720.8946,24.99672</point>
  <point>0.6486402,0.7610953,0,-0.7610953,0.6486402,0,0,0,1,437.2096,630.5392,23.8009</point>
  <point>0.5276251,0.8494867,0,-0.8494867,0.5276251,0,0,0,1,480.4028,721.7089,24.99915</point>
  <point>0.6486402,0.7610953,0,-0.7610953,0.6486402,0,0,0,1,437.7298,631.2361,23.80251</point>
  <point>-0.859461,0.5112149,0,-0.5112149,-0.859461,0,0,0,1,458.4704,754.342,30.5588</point>
  <point>0.8225027,-0.5687624,0,0.5687624,0.8225027,0,0,0,1,441.1799,632.2973,23.79122</point>
  <point>-0.7920817,0.6104266,0,-0.6104266,-0.7920817,0,0,0,1,457.6908,754.9272,30.5588</point>
  <point>0.6018354,0.7986219,0,-0.7986219,0.6018354,0,0,0,1,444.2254,632.9366,22.77945</point>
  <point>0.602633,0.7980186,0,-0.7980186,0.602633,0,0,0,1,439.71,629.016,27.70491</point>
  <point>0.2238833,0.9746186,0,-0.9746186,0.2238833,0,0,0,1,489.9665,678.1475,20.39778</point>
  <point>0.6711791,0.741298,0,-0.741298,0.6711791,0,0,0,1,476.4071,657.4859,20.72169</point>
  <point>-0.9543276,-0.298774,0,0.298774,-0.9543276,0,0,0,1,464.1846,734.4826,20.23672</point>
  <point>0.06257108,0.9980529,0,-0.9980529,0.06257108,0,0,0,1,488.0095,691.6738,25.75111</point>
  <point>0.6151845,0.7883968,0,-0.7883968,0.6151845,0,0,0,1,479.0889,720.0373,20.3882</point>
  <point>-0.8283768,0.5601714,0,-0.5601714,-0.8283768,0,0,0,1,479.951,717.578,20.40217</point>
  <point>-0.4594671,0.8882084,0,-0.8882084,-0.4594671,0,0,0,1,488.012,686.7894,25.75111</point>
  <point>0.9974806,-0.07094037,0,0.07094037,0.9974806,0,0,0,1,494.442,690.832,13.26551</point>
  <point>0.1065935,0.9943027,0,-0.9943027,0.1065935,0,0,0,1,489.029,700.923,20.32689</point>
  <point>0.07572419,0.9971313,0,-0.9971313,0.07572419,0,0,0,1,490.414,681.2612,20.40284</point>
  <point>-0.664036,0.7477008,0,-0.7477008,-0.664036,0,0,0,1,456.114,755.053,24.69995</point>
  <point>0.6018354,0.7986219,0,-0.7986219,0.6018354,0,0,0,1,447.4621,637.3841,22.05891</point>
  <point>-0.9999844,-0.005592706,0,0.005592706,-0.9999844,0,0,0,1,495.014,699.869,13.26556</point>
  <point>-0.9911256,0.133014,0,-0.133014,-0.9911256,0,0,0,1,492.6222,684.0176,25.75111</point>
  <point>0.9966853,-0.08172355,0,0.08172355,0.9966853,0,0,0,1,494.5824,692.7001,20.31355</point>
  <point>0.9151213,0.4031912,0,-0.4031912,0.9151213,0,0,0,1,461.9908,740.9742,20.27644</point>
  <point>-0.6919659,0.7219388,0,-0.7219388,-0.6919659,0,0,0,1,470.2292,784.8746,17.60525</point>
  <point>0.3210104,0.9470756,0,-0.9470756,0.3210104,0,0,0,1,504.687,724.786,26.47582</point>
  <point>-0.1397449,0.9901875,0,-0.9901875,-0.1397449,0,0,0,1,454.747,758.977,20.06406</point>
  <point>0.07572419,0.9971313,0,-0.9971313,0.07572419,0,0,0,1,490.4218,682.073,20.39987</point>
  <point>0.9920725,-0.1256669,0,0.1256669,0.9920725,0,0,0,1,464.165,654.126,26.88234</point>
</points>